{
  "scripts":[
    {
      "name":"",
      "text":"ある日の朝方"
    },
    {
      "name":"???",
      "text":"もう金が無い..."
    },
    {
      "name":"???",
      "text":"まあ元はといえば、あの店主がハズレの台を教えやがったのが悪い。"
    },
    {
      "name":"???",
      "text":"だから俺には何の罪もない!"
    },
    {
      "name":"",
      "text":"パチンコ狂いの野郎が居た。"
    },
    {
      "name":"",
      "text":"その名も、<font color='#e55'>信州くん</font>である。"
    },
    {
      "name":"信州くん",
      "text":"所持金はもう1568円しかないが、今日こそは倍にしてやる。"
    },
    {
      "name":"",
      "text":"頭が悪い。"
    },
    {
      "name":"信州くん",
      "text":"ん?"
    },
    {
      "name":"信州くん",
      "text":"こんな所に祠なんてあったか?"
    },
    {
      "name":"",
      "text":"信州くんは、見慣れない古ぼけた祠を発見した。"
    },
    {
      "name":"信州くん",
      "text":"祠の癖に、なんだか俺を見下しているような雰囲気を感じるな..."
    },
    {
      "name":"",
      "text":"いくら祠でも見下すレベルだという自覚がまるで無い。"
    },
    {
      "name":"信州くん",
      "text":"なんかムカつくから、景観のためにも撤去してやるか。"
    },
    {
      "name":"",
      "text":"誰かこいつに常識を教えてやってくれ。"
    }
  ]
}